LICENSE
MANIFEST.in
README.rst
setup.cfg
setup.py
webtemplate_dpaw/__init__.py
webtemplate_dpaw.egg-info/PKG-INFO
webtemplate_dpaw.egg-info/SOURCES.txt
webtemplate_dpaw.egg-info/dependency_links.txt
webtemplate_dpaw.egg-info/requires.txt
webtemplate_dpaw.egg-info/top_level.txt
webtemplate_dpaw/static/favicon.ico
webtemplate_dpaw/static/css/dpaw-custom.css
webtemplate_dpaw/static/css/dpaw-internet.css
webtemplate_dpaw/static/img/dpaw_logo_small.png
webtemplate_dpaw/static/img/logo-dpaw.gif
webtemplate_dpaw/static/img/top-bg.gif
webtemplate_dpaw/static/img/waTextBlack_80-bluebg.gif
webtemplate_dpaw/templates/webtemplate_dpaw/base.html
webtemplate_dpaw/templates/webtemplate_dpaw/base_dbca.html
webtemplate_dpaw/templates/webtemplate_dpaw/base_foundation.html
webtemplate_dpaw/templates/webtemplate_dpaw/base_internet.html
webtemplate_dpaw/templates/webtemplate_dpaw/logged_out.html
webtemplate_dpaw/templates/webtemplate_dpaw/login.html