Metadata-Version: 1.1
Name: webtemplate-dpaw
Version: 0.4.8
Summary: Base HTML templates for DBCA Django projects
Home-page: https://github.com/parksandwildlife/webtemplate
Author: Ashley Felton
Author-email: asi@dbca.wa.gov.au
License: Apache License, Version 2.0
Keywords: django,html,template
Platform: UNKNOWN
Classifier: Framework :: Django
Classifier: Framework :: Django :: 1.10
Classifier: Framework :: Django :: 1.11
Classifier: Environment :: Web Environment
Classifier: Intended Audience :: Developers
Classifier: Development Status :: 5 - Production/Stable
Classifier: License :: OSI Approved :: Apache Software License
Classifier: Programming Language :: Python
Classifier: Programming Language :: Python :: 2
Classifier: Programming Language :: Python :: 2.7
Classifier: Topic :: Software Development :: Libraries
Classifier: Topic :: Software Development :: Libraries :: Python Modules
